{"cameraMode":{"drawMode":0,"name":"Shaded","section":"Shading Mode"},"sceneLighting":false,"audioPlay":false,"sceneViewState":{"m_AlwaysRefresh":false,"showFog":true,"showSkybox":false,"showFlares":true,"showImageEffects":true,"showParticleSystems":true,"showVisualEffectGraphs":true,"m_FxEnabled":true},"in2DMode":false,"pivot":{"x":0.0,"y":0.2200000286102295,"z":3.640000104904175},"rotation":{"x":0.29123908281326296,"y":-0.041601382195949557,"z":0.012678203172981739,"w":0.9556624293327332},"size":1.299038290977478,"orthographic":false}